compr.py
compr-0.1.4.dist-info/LICENSE
compr-0.1.4.dist-info/METADATA
compr-0.1.4.dist-info/WHEEL
compr-0.1.4.dist-info/top_level.txt
compr-0.1.4.dist-info/RECORD
